{
  "info": {
    "_postman_id": "b2aa4f1c-5d4b-4d93-9f6f-f8c3f8a8d005",
    "name": "TeamHub - 05 Users",
    "schema": "https://schema.getpostman.com/json/collection/v2.1.0/collection.json"
  },
  "variable": [{ "key": "baseUrl", "value": "http://localhost:4000/api" }],
  "item": [
    {
      "name": "Search users (global)",
      "request": {
        "method": "GET",
        "header": [{ "key": "Authorization", "value": "Bearer {{accessToken}}" }],
        "url": {
          "raw": "{{baseUrl}}/users/search?q={{searchQ}}&limit=10",
          "host": ["{{baseUrl}}"],
          "path": ["users", "search"],
          "query": [
            { "key": "q", "value": "{{searchQ}}" },
            { "key": "limit", "value": "10" }
          ]
        }
      }
    },
    {
      "name": "Search users (workspace scoped)",
      "request": {
        "method": "GET",
        "header": [{ "key": "Authorization", "value": "Bearer {{accessToken}}" }],
        "url": {
          "raw": "{{baseUrl}}/users/search?q={{searchQ}}&workspaceId={{workspaceId}}&limit=10",
          "host": ["{{baseUrl}}"],
          "path": ["users", "search"],
          "query": [
            { "key": "q", "value": "{{searchQ}}" },
            { "key": "workspaceId", "value": "{{workspaceId}}" },
            { "key": "limit", "value": "10" }
          ]
        }
      }
    }
  ]
}
